street_view_mcp/__init__.py
street_view_mcp/main.py
street_view_mcp/server.py
street_view_mcp/street_view.py
iflow_mcp_street_view_mcp-0.1.1.dist-info/METADATA
iflow_mcp_street_view_mcp-0.1.1.dist-info/WHEEL
iflow_mcp_street_view_mcp-0.1.1.dist-info/entry_points.txt
iflow_mcp_street_view_mcp-0.1.1.dist-info/RECORD
