Metadata-Version: 2.4
Name: iflow-mcp_street-view-mcp
Version: 0.1.1
Summary: MCP for interacting with Street View imagery
Project-URL: Homepage, https://github.com/yourusername/street-view-mcp
Project-URL: Bug Tracker, https://github.com/yourusername/street-view-mcp/issues
Author-email: Your Name <your.email@example.com>
License: MIT
Requires-Python: >=3.10
Requires-Dist: fastmcp
Requires-Dist: pillow
Requires-Dist: python-dotenv
Requires-Dist: requests
